ndots/LICENSE.txt
ndots/__init__.py
ndots/ndots.py
ndots-1.0.0.post0.dist-info/METADATA
ndots-1.0.0.post0.dist-info/WHEEL
ndots-1.0.0.post0.dist-info/top_level.txt
ndots-1.0.0.post0.dist-info/RECORD
