Metadata-Version: 2.2
Name: ndots
Version: 1.0.0.post0
Summary: ndots - matrix fonts
Author-email: Ruud van der Ham <rt.van.der.ham@gmail.com>
Project-URL: Homepage, https://github.com/salabim/ndots
Project-URL: Repository, https://github.com/salabim/ndots
Classifier: Development Status :: 5 - Production/Stable
Classifier: License :: OSI Approved :: MIT License
Classifier: Programming Language :: Python :: 3 :: Only
Requires-Python: >=3.7
